covid_big_bappenas/__init__.py
covid_big_bappenas/main.py
covid_big_bappenas-1.1.dist-info/LICENSE
covid_big_bappenas-1.1.dist-info/METADATA
covid_big_bappenas-1.1.dist-info/WHEEL
covid_big_bappenas-1.1.dist-info/entry_points.txt
covid_big_bappenas-1.1.dist-info/top_level.txt
covid_big_bappenas-1.1.dist-info/RECORD
