Metadata-Version: 2.1
Name: covid-big-bappenas
Version: 1.1
Summary: An Covid-Big-Bappenas package
Home-page: https://github.com/emhayusa/covid-big-bappenas
Author: Muhammad Hasannudin Yusa
Author-email: emhayusa@gmail.com
License: UNKNOWN
Platform: UNKNOWN
Classifier: Programming Language :: Python :: 3
Classifier: License :: OSI Approved :: MIT License
Classifier: Operating System :: OS Independent
Requires-Dist: Click
Requires-Dist: requests
